laserfocus/__init__.py
laserfocus/utils/__init__.py
laserfocus/utils/exception.py
laserfocus/utils/logger.py
laserfocus/utils/managers/__init__.py
laserfocus/utils/managers/database.py
laserfocus/utils/managers/scopes.py
laserfocus-0.1.26.dist-info/licenses/LICENSE
laserfocus-0.1.26.dist-info/METADATA
laserfocus-0.1.26.dist-info/WHEEL
laserfocus-0.1.26.dist-info/top_level.txt
laserfocus-0.1.26.dist-info/RECORD
